Metadata-Version: 1.0
Name: cheweyapi
Version: 0.2
Summary: An API wrapper for the chewey bot's api.
Home-page: http://github.com/iWeeti/cheweyapi-python
Author: iWeeti
Author-email: maaninkaveeti@gmail.com
License: MIT
Platform: UNKNOWN
